multi_bioservices/__init__.py
multi_bioservices/biodbnet/__init__.py
multi_bioservices/biodbnet/db2db.py
multi_bioservices/biodbnet/dbFind.py
multi_bioservices/biodbnet/dbOrtho.py
multi_bioservices/biodbnet/dbReport.py
multi_bioservices/biodbnet/dbWalk.py
multi_bioservices/biodbnet/input_database.py
multi_bioservices/biodbnet/output_database.py
multi_bioservices/biodbnet/taxon_id.py
multi_bioservices/utils.py
multi_bioservices-3.1.2.dist-info/METADATA
multi_bioservices-3.1.2.dist-info/WHEEL
multi_bioservices-3.1.2.dist-info/RECORD
