Metadata-Version: 2.1
Name: multi_bioservices
Version: 3.1.2
Summary: This is a multithreaded version of various BioServices functions
Author: Josh Loecker
Author-email: joshloecker@icloud.com
Requires-Python: >=3.9,<4.0
Classifier: Programming Language :: Python :: 3
Classifier: Programming Language :: Python :: 3.9
Classifier: Programming Language :: Python :: 3.10
Classifier: Programming Language :: Python :: 3.11
Classifier: Programming Language :: Python :: 3.12
Requires-Dist: aiosqlite (>=0.19.0)
Requires-Dist: bioservices (<2)
Requires-Dist: pandas (>=1.4.4)
